alecci/__init__.py
alecci/__main__.py
alecci/compiling/__init__.py
alecci/compiling/base_types.py
alecci/compiling/compiler.py
alecci/compiling/threading_utils.py
alecci/parsing/__init__.py
alecci/parsing/a_lexer.py
alecci/parsing/a_parser.py
alecci/parsing/globals.py
alecci/parsing/parsetab.py
alecci/ply/__init__.py
alecci/ply/lex.py
alecci/ply/yacc.py
alecci-1.1.0.dist-info/METADATA
alecci-1.1.0.dist-info/WHEEL
alecci-1.1.0.dist-info/entry_points.txt
alecci-1.1.0.dist-info/top_level.txt
alecci-1.1.0.dist-info/RECORD
